cloudcix/__init__.py
cloudcix/auth.py
cloudcix/client.py
cloudcix/conf.py
cloudcix/exceptions.py
cloudcix/lock.py
cloudcix/lock_backend.py
cloudcix/utils.py
cloudcix/api/__init__.py
cloudcix/api/app_manager.py
cloudcix/api/asset.py
cloudcix/api/circuit.py
cloudcix/api/compute.py
cloudcix/api/contact.py
cloudcix/api/contacts.py
cloudcix/api/dcim.py
cloudcix/api/documentation.py
cloudcix/api/financial.py
cloudcix/api/helpdesk.py
cloudcix/api/iaas.py
cloudcix/api/membership.py
cloudcix/api/otp.py
cloudcix/api/pat.py
cloudcix/api/plot.py
cloudcix/api/reporting.py
cloudcix/api/repository.py
cloudcix/api/scheduler.py
cloudcix/api/scm.py
cloudcix/api/security.py
cloudcix/api/support.py
cloudcix/api/training.py
cloudcix/api/vault.py
cloudcix/rcc/__init__.py
cloudcix/rcc/channel_codes.py
cloudcix/rcc/http.py
cloudcix/rcc/lsh.py
cloudcix/rcc/pylxd_api.py
cloudcix/rcc/response.py
cloudcix/rcc/ssh.py
cloudcix-5.0.4.dist-info/LICENSE
cloudcix-5.0.4.dist-info/METADATA
cloudcix-5.0.4.dist-info/WHEEL
cloudcix-5.0.4.dist-info/top_level.txt
cloudcix-5.0.4.dist-info/RECORD
