Metadata-Version: 2.1
Name: cloudcix
Version: 5.0.4
Summary: Python3 bindings and utils for CloudCIX API.
Author-email: CloudCIX <developers@cloudcix.com>
License: Copyright 2015 CloudCIX
Project-URL: Homepage, https://python-cloudcix.readthedocs.io/en/latest/
Keywords: CloudCIX SDK
Classifier: Development Status :: 5 - Production/Stable
Classifier: Intended Audience :: Information Technology
Classifier: Intended Audience :: Developers
Classifier: License :: OSI Approved :: Apache Software License
Classifier: Natural Language :: English
Classifier: Programming Language :: Python :: 3
Requires-Python: >=3.7
License-File: LICENSE
Requires-Dist: jaeger-client
Requires-Dist: jinja2
Requires-Dist: netaddr
Requires-Dist: opentracing
Requires-Dist: paramiko
Requires-Dist: psycopg2-binary
Requires-Dist: pylxd
Requires-Dist: python-dateutil
Requires-Dist: requests
